gptroles/__init__.py
gptroles/gpt.py
gptroles/main.py
gptroles/prompts.py
gptroles/settings.py
gptroles/ui/__init__.py
gptroles/ui/indicator.py
gptroles/ui/mainwindow.py
gptroles/ui/settings.py
gptroles/ui/utils.py
gptroles/ui/web/.parcelrc
gptroles/ui/web/dist/chatpage.153c3a09.css
gptroles/ui/web/dist/chatpage.153c3a09.css.map
gptroles/ui/web/dist/chatpage.17936317.js
gptroles/ui/web/dist/chatpage.17936317.js.map
gptroles/ui/web/dist/chatpage.1ee3acf6.js
gptroles/ui/web/dist/chatpage.1ee3acf6.js.map
gptroles/ui/web/dist/chatpage.28944a1e.css
gptroles/ui/web/dist/chatpage.28944a1e.css.map
gptroles/ui/web/dist/chatpage.3361cb26.css
gptroles/ui/web/dist/chatpage.3361cb26.css.map
gptroles/ui/web/dist/chatpage.5d2f6e12.js
gptroles/ui/web/dist/chatpage.5d2f6e12.js.map
gptroles/ui/web/dist/chatpage.html
gptroles/ui/web/dist/highlight.min.css
gptroles/ui/web/dist/highlight.min.js
gptroles/ui/web/dist/marked.min.js
gptroles/ui/web/package-lock.json
gptroles/ui/web/package.json
gptroles/ui/web/package.sh
gptroles/ui/web/postpackage.sh
gptroles/ui/web/release.zip
gptroles/ui/web/src/chatpage.html
gptroles/ui/web/src/index.js
gptroles/ui/web/src/static/highlight.min.css
gptroles/ui/web/src/static/highlight.min.js
gptroles/ui/web/src/static/marked.min.js
gptroles/ui/web/src/style.css
gptroles/ui/web/src/term.js
gptroles/ui/widgets/__init__.py
gptroles/ui/widgets/borderlesswindow.py
gptroles/ui/widgets/chatbox.py
gptroles/ui/widgets/chatmsg.py
gptroles/ui/widgets/netprompts.py
gptroles/ui/widgets/nterminal.py
gptroles/ui/widgets/terminal/__init__.py
gptroles/ui/widgets/terminal/console.py
gptroles/ui/widgets/terminal/settingsdialog.py
gptroles/utils.py
gptroles-0.1.5.dist-info/METADATA
gptroles-0.1.5.dist-info/WHEEL
gptroles-0.1.5.dist-info/entry_points.txt
gptroles-0.1.5.dist-info/RECORD
