Metadata-Version: 2.1
Name: gptroles
Version: 0.1.5
Summary: Interact with chatgpt and assign different roles
Home-page: https://github.com/blipk/gptroles
License: MIT
Keywords: gptroles,ChatGPT,GPT,LLM,ML
Author: Blipk A.D.
Requires-Python: >=3.10,<4.0
Classifier: License :: OSI Approved :: MIT License
Classifier: Programming Language :: Python :: 3
Classifier: Programming Language :: Python :: 3.10
Classifier: Programming Language :: Python :: 3.11
Classifier: Topic :: Software Development :: Libraries :: Python Modules
Requires-Dist: appdirs (>=1.4.4,<2.0.0)
Requires-Dist: langchain (>=0.0.126,<0.0.127)
Requires-Dist: openai (>=0.27.2)
Requires-Dist: pydantic (>=1.10.7,<2.0.0)
Requires-Dist: pygments (>=2.14.0,<3.0.0)
Requires-Dist: pyqt6 (>=6.4.2)
Requires-Dist: pyqt6-webengine (>=6.4.0)
Requires-Dist: toml (>=0.10.2,<0.11.0)
Project-URL: Documentation, https://github.com/blipk/gptroles
Project-URL: Repository, https://github.com/blipk/gptroles
